tests/__init__.py
tests/test_configuration.py
xpipe/__init__.py
xpipe/config/__init__.py
xpipe/config/config.py
xpipe/config/loader.py
xpipe/config/node.py
xpipe/config/objects.py
xpipe/config/tag.py
xpipe/config/utils.py
xpipe/config/variables.py
xpipe/template/__init__.py
xpipe/template/parameter.py
xpipe/template/template.py
xpipe/template/utils.py
XPipe-1.1.1.dist-info/LICENSE
XPipe-1.1.1.dist-info/METADATA
XPipe-1.1.1.dist-info/WHEEL
XPipe-1.1.1.dist-info/top_level.txt
XPipe-1.1.1.dist-info/RECORD
