Metadata-Version: 2.1
Name: XPipe
Version: 1.1.1
Summary: Standardize your ML projects
Home-page: UNKNOWN
Author: Jules Tevissen
License: MIT
Platform: UNKNOWN
Classifier: Programming Language :: Python :: 3
Classifier: Programming Language :: Python :: 3.6
Classifier: Programming Language :: Python :: 3.7
Classifier: Programming Language :: Python :: 3.8
Classifier: Programming Language :: Python :: 3.9
Classifier: Programming Language :: Python :: 3.10
Requires-Python: >=3.6
Requires-Dist: pyyaml
Requires-Dist: jinja2
